{"_ts":[1501581229,1501625335,1501669230,1501713332,1501757003,1501800736,1501844859],"_r":{"breakdown":{"html":{"bytes":[108439,112414,113033,112977,111328,111152,110648],"requests":[16,18,18,18,16,16,16]},"js":{"bytes":[1085812,1083314,1083450,1082841,1083708,1083571,1084730],"requests":[43,43,43,43,43,43,43]},"css":{"bytes":[176081,176087,175716,176086,176081,176087,176085],"requests":[11,11,11,11,11,11,11]},"image":{"bytes":[272113,271337,271362,271757,272233,272287,272007],"requests":[54,51,51,52,52,52,51]},"flash":{"bytes":[0,0,0,0,0,0,0],"requests":[0,0,0,0,0,0,0]},"font":{"bytes":[83652,83651,83651,83652,83652,83651,83646],"requests":[5,5,5,5,5,5,5]},"other":{"bytes":[3623,3622,4266,3624,3624,4268,3624],"requests":[4,4,9,4,4,9,4]}},"date":[1501581229,1501625335,1501669230,1501713332,1501757003,1501800736,1501844859],"domElements":[1589,1589,1589,1589,1589,1589,1589],"domInteractive":[3594,2674,3235,3451,3922,4098,3592],"firstPaint":[1861,1408,1618,1760,1658,1970,1554],"fullyLoaded":[12096,11640,9943,10732,14340,10268,11499],"id":["170801_1R_Q3V","170801_E4_1JFJ","170802_PD_RTF","170802_C6_1N3S","170803_PD_1A08","170803_KW_29XT","170804_TJ_YKX"],"loadTime":[10525,10131,8522,9376,13013,9116,10039],"render":[2461,1772,2164,2227,2086,2701,2064],"SpeedIndex":[5015,3796,4364,4196,5142,5005,4596],"TTFB":[885,707,796,785,707,1095,728],"videoFrames":[[{"_i":"frame_0000.jpg","_t":0,"_vc":0},{"_i":"frame_0025.jpg","_t":2500,"_vc":14},{"_i":"frame_0027.jpg","_t":2700,"_vc":15},{"_i":"frame_0029.jpg","_t":2900,"_vc":33},{"_i":"frame_0056.jpg","_t":5600,"_vc":48},{"_i":"frame_0063.jpg","_t":6300,"_vc":100}],[{"_i":"frame_0000.jpg","_t":0,"_vc":0},{"_i":"frame_0018.jpg","_t":1800,"_vc":14},{"_i":"frame_0020.jpg","_t":2000,"_vc":15},{"_i":"frame_0023.jpg","_t":2300,"_vc":33},{"_i":"frame_0034.jpg","_t":3400,"_vc":48},{"_i":"frame_0041.jpg","_t":4100,"_vc":48},{"_i":"frame_0049.jpg","_t":4900,"_vc":48},{"_i":"frame_0050.jpg","_t":5000,"_vc":100}],[{"_i":"frame_0000.jpg","_t":0,"_vc":0},{"_i":"frame_0022.jpg","_t":2200,"_vc":15},{"_i":"frame_0036.jpg","_t":3600,"_vc":33},{"_i":"frame_0042.jpg","_t":4200,"_vc":48},{"_i":"frame_0048.jpg","_t":4800,"_vc":48},{"_i":"frame_0050.jpg","_t":5000,"_vc":48},{"_i":"frame_0053.jpg","_t":5300,"_vc":100}],[{"_i":"frame_0000.jpg","_t":0,"_vc":0},{"_i":"frame_0022.jpg","_t":2200,"_vc":13},{"_i":"frame_0024.jpg","_t":2400,"_vc":14},{"_i":"frame_0031.jpg","_t":3100,"_vc":32},{"_i":"frame_0041.jpg","_t":4100,"_vc":55},{"_i":"frame_0046.jpg","_t":4600,"_vc":55},{"_i":"frame_0050.jpg","_t":5000,"_vc":55},{"_i":"frame_0053.jpg","_t":5300,"_vc":100}],[{"_i":"frame_0000.jpg","_t":0,"_vc":0},{"_i":"frame_0021.jpg","_t":2100,"_vc":13},{"_i":"frame_0026.jpg","_t":2600,"_vc":14},{"_i":"frame_0030.jpg","_t":3000,"_vc":32},{"_i":"frame_0039.jpg","_t":3900,"_vc":32},{"_i":"frame_0056.jpg","_t":5600,"_vc":55},{"_i":"frame_0063.jpg","_t":6300,"_vc":55},{"_i":"frame_0067.jpg","_t":6700,"_vc":100}],[{"_i":"frame_0000.jpg","_t":0,"_vc":0},{"_i":"frame_0027.jpg","_t":2700,"_vc":15},{"_i":"frame_0036.jpg","_t":3600,"_vc":33},{"_i":"frame_0038.jpg","_t":3800,"_vc":33},{"_i":"frame_0052.jpg","_t":5200,"_vc":48},{"_i":"frame_0058.jpg","_t":5800,"_vc":48},{"_i":"frame_0061.jpg","_t":6100,"_vc":100}],[{"_i":"frame_0000.jpg","_t":0,"_vc":0},{"_i":"frame_0021.jpg","_t":2100,"_vc":13},{"_i":"frame_0022.jpg","_t":2200,"_vc":15},{"_i":"frame_0031.jpg","_t":3100,"_vc":33},{"_i":"frame_0038.jpg","_t":3800,"_vc":33},{"_i":"frame_0047.jpg","_t":4700,"_vc":48},{"_i":"frame_0054.jpg","_t":5400,"_vc":48},{"_i":"frame_0058.jpg","_t":5800,"_vc":100}]],"visualComplete":[6300,5000,5300,5300,6700,6100,5800],"lighthouse":[null,null,null,null,null,null,null],"pagespeed":[68,68,69,69,68,69,68]}}