{"_ts":[1487668082,1487712084,1487755635],"_r":{"breakdown":{"html":{"bytes":[60853,59672,60653],"requests":[8,8,8]},"js":{"bytes":[484418,379688,378932],"requests":[63,18,18]},"css":{"bytes":[85913,63985,63985],"requests":[17,2,2]},"image":{"bytes":[556322,548572,552996],"requests":[37,37,37]},"flash":{"bytes":[0,0,0],"requests":[0,0,0]},"font":{"bytes":[83378,83377,83379],"requests":[5,5,5]},"other":{"bytes":[2116,1437,1437],"requests":[3,2,2]}},"date":[1487668082,1487712084,1487755635],"domElements":[2608,2536,2536],"domInteractive":[5556,4787,13532],"firstPaint":[4069,4031,12563],"fullyLoaded":[8194,13175,25531],"id":["170221_85_FVQ","170221_FD_2FYW","170222_6C_DMF4"],"loadTime":[7913,12469,25185],"render":[4497,4394,12692],"SpeedIndex":[6893,6951,14504],"TTFB":[3067,4,11795],"videoFrames":[[{"_t":0,"_vc":0},{"_t":4500,"_vc":0},{"_t":4700,"_vc":0},{"_t":4800,"_vc":0},{"_t":4900,"_vc":0},{"_t":5100,"_vc":0},{"_t":5300,"_vc":0},{"_t":5500,"_vc":0},{"_t":5700,"_vc":0},{"_t":5800,"_vc":0},{"_t":6000,"_vc":0},{"_t":6200,"_vc":0},{"_t":6300,"_vc":0},{"_t":6500,"_vc":0},{"_t":6600,"_vc":0},{"_t":6800,"_vc":61},{"_t":7000,"_vc":83},{"_t":7200,"_vc":100}],[{"_t":0,"_vc":0},{"_t":4400,"_vc":0},{"_t":4500,"_vc":0},{"_t":4700,"_vc":0},{"_t":4900,"_vc":0},{"_t":5000,"_vc":0},{"_t":5200,"_vc":0},{"_t":5400,"_vc":0},{"_t":5600,"_vc":0},{"_t":5800,"_vc":0},{"_t":5900,"_vc":0},{"_t":6000,"_vc":0},{"_t":6200,"_vc":0},{"_t":6400,"_vc":64},{"_t":6700,"_vc":65},{"_t":7200,"_vc":66},{"_t":7300,"_vc":70},{"_t":7500,"_vc":74},{"_t":7900,"_vc":79},{"_t":8000,"_vc":84},{"_t":8200,"_vc":87},{"_t":8500,"_vc":100}],[{"_t":0,"_vc":0},{"_t":12700,"_vc":0},{"_t":12900,"_vc":0},{"_t":13100,"_vc":0},{"_t":13300,"_vc":0},{"_t":13400,"_vc":0},{"_t":13600,"_vc":0},{"_t":13700,"_vc":0},{"_t":13900,"_vc":0},{"_t":14100,"_vc":0},{"_t":14300,"_vc":0},{"_t":14500,"_vc":79},{"_t":14600,"_vc":100}]],"visualComplete":[7189,8501,14592]}}